potreepublisher/Publisher.py
potreepublisher/__init__.py
potreepublisher/__main__.py
potreepublisher/main.py
potreepublisher/potree_server_config.yaml
potreepublisher/viewer_templates/template_folder.html
potreepublisher/viewer_templates/template_single_file.html
potreepublisher-0.1.5.dist-info/entry_points.txt
potreepublisher-0.1.5.dist-info/LICENSE
potreepublisher-0.1.5.dist-info/WHEEL
potreepublisher-0.1.5.dist-info/METADATA
potreepublisher-0.1.5.dist-info/RECORD
