Metadata-Version: 2.1
Name: potreepublisher
Version: 0.1.5
Summary: Small CLI to quickly publish a single LAS file or a whole folder to a Potree server.
License: MIT
Author: Elie-Alban LESCOUT
Author-email: elie-alban.lescout@ensg.eu
Requires-Python: >=3.7,<4.0
Classifier: License :: OSI Approved :: MIT License
Classifier: Programming Language :: Python :: 3
Classifier: Programming Language :: Python :: 3.10
Classifier: Programming Language :: Python :: 3.7
Classifier: Programming Language :: Python :: 3.8
Classifier: Programming Language :: Python :: 3.9
Requires-Dist: PyYAML (>=6.0,<7.0)
Requires-Dist: typer[all] (>=0.4.0,<0.5.0)
